minke/__init__.py
minke/admin.py
minke/apps.py
minke/engine.py
minke/exceptions.py
minke/fabrictools.py
minke/filters.py
minke/forms.py
minke/helpers.py
minke/messages.py
minke/models.py
minke/serializers.py
minke/sessions.py
minke/settings.py
minke/tasks.py
minke/urls.py
minke/utils.py
minke/views.py
minke/contrib/__init__.py
minke/contrib/commands/__init__.py
minke/contrib/commands/admin.py
minke/contrib/commands/apps.py
minke/contrib/commands/forms.py
minke/contrib/commands/models.py
minke/contrib/commands/sessions.py
minke/contrib/commands/tests.py
minke/contrib/commands/migrations/0001_initial.py
minke/contrib/commands/migrations/__init__.py
minke/management/__init__.py
minke/management/commands/__init__.py
minke/management/commands/minkeadm.py
minke/management/commands/minkerun.py
minke/migrations/0001_initial.py
minke/migrations/0002_auto_20180619_1703.py
minke/migrations/0003_auto_20190326_1648.py
minke/migrations/0004_auto_20190703_1319.py
minke/migrations/0005_auto_20190810_1412.py
minke/migrations/0006_auto_20200108_1333.py
minke/migrations/0007_auto_20230404_1646.py
minke/migrations/0008_auto_20230405_2153.py
minke/migrations/0009_remove_minkesession_session_data.py
minke/migrations/__init__.py
minke/static/minke/css/minke.css
minke/static/minke/css/minke_form.css
minke/static/minke/js/minke.js
minke/templates/minke/change_form.html
minke/templates/minke/change_list.html
minke/templates/minke/change_list_results.html
minke/templates/minke/message_toggle.html
minke/templates/minke/minke_form.html
minke/templates/minke/session.html
minke/templates/minke/session_change_list.html
minke/templates/minke/session_select.html
minke/templates/minke/session_summary.html
minke/templates/minke/session_switch.html
minke/templatetags/__init__.py
minke/templatetags/minke.py
django_minke-1.3.2.dev0.dist-info/LICENCE
django_minke-1.3.2.dev0.dist-info/METADATA
django_minke-1.3.2.dev0.dist-info/WHEEL
django_minke-1.3.2.dev0.dist-info/top_level.txt
django_minke-1.3.2.dev0.dist-info/zip-safe
django_minke-1.3.2.dev0.dist-info/RECORD
