Metadata-Version: 2.1
Name: django-minke
Version: 1.3.2.dev0
Summary: Django- and fabric-based building toolkit for remote-control- and configuration-management-systems.
Author: Thomas Leichtfuß
Author-email: thomas.leichtfuss@posteo.de
License: BSD License
Platform: OS Independent
Classifier: Development Status :: 5 - Production/Stable
Classifier: Framework :: Django
Classifier: Environment :: Web Environment
Classifier: Intended Audience :: Developers
Classifier: Intended Audience :: System Administrators
Classifier: License :: OSI Approved :: BSD License
Classifier: Operating System :: OS Independent
Classifier: Programming Language :: Python
Classifier: Programming Language :: Python :: 3
Classifier: Programming Language :: Python :: 3.4
Classifier: Programming Language :: Python :: 3.5
Classifier: Programming Language :: Python :: 3.6
Classifier: Programming Language :: Python :: 3.7
Classifier: Topic :: Internet :: WWW/HTTP :: Dynamic Content
Classifier: Topic :: Software Development
Classifier: Topic :: Software Development :: Libraries :: Application Frameworks
Classifier: Topic :: System :: Networking :: Monitoring
Classifier: Topic :: System :: Systems Administration
License-File: LICENCE
Requires-Dist: Django<3.0,>=1.11
Requires-Dist: fabric2>=2.4.0
Requires-Dist: celery<=5.3.1,>=4.2.2
Requires-Dist: djangorestframework>=3.9.2
Requires-Dist: pyyaml
